osc_kreuz/__init__.py
osc_kreuz/_version.py
osc_kreuz/config.py
osc_kreuz/config_default.yml
osc_kreuz/conversionsTools.py
osc_kreuz/coordinates.py
osc_kreuz/osc_kreuz.py
osc_kreuz/osccomcenter.py
osc_kreuz/renderer.py
osc_kreuz/soundobject.py
osc_kreuz/str_keys_conventions.py
osc_kreuz-1.5.1.dist-info/LICENSE
osc_kreuz-1.5.1.dist-info/METADATA
osc_kreuz-1.5.1.dist-info/WHEEL
osc_kreuz-1.5.1.dist-info/entry_points.txt
osc_kreuz-1.5.1.dist-info/top_level.txt
osc_kreuz-1.5.1.dist-info/RECORD
