Metadata-Version: 2.2
Name: osc_kreuz
Version: 1.5.1
Summary: A tool for routing incoming OSC messages to different renderers for spatial audio
Author-email: Max Weidauer <weidauer@campus.tu-berlin.de>, Fares Schulz <fares.schulz@tu-berlin.de>, Paul Schuladen <example@example.org>
Maintainer-email: Max Weidauer <weidauer@campus.tu-berlin.de>
License:                     GNU GENERAL PUBLIC LICENSE
Project-URL: Github, https://github.com/tu-studio/osc-kreuz
Project-URL: Issues, https://github.com/tu-studio/osc-kreuz/issues
Requires-Python: >=3.10
License-File: LICENSE
Requires-Dist: numpy
Requires-Dist: python-osc
Requires-Dist: click
Requires-Dist: pyYAML
Provides-Extra: tests
Requires-Dist: pytest; extra == "tests"
Requires-Dist: pyfar; extra == "tests"
Requires-Dist: pytest-cov; extra == "tests"
